hello/__init__.py
hello/hello.py
vidstream_3-0.0.1.dist-info/LICENSE
vidstream_3-0.0.1.dist-info/METADATA
vidstream_3-0.0.1.dist-info/WHEEL
vidstream_3-0.0.1.dist-info/top_level.txt
vidstream_3-0.0.1.dist-info/RECORD
